test_sdk/__init__.py
test_sdk/sum_arun_test.py
test_sdk/test_functions.py
sum_arun_test-0.1.3.dist-info/METADATA
sum_arun_test-0.1.3.dist-info/WHEEL
sum_arun_test-0.1.3.dist-info/top_level.txt
sum_arun_test-0.1.3.dist-info/RECORD
