Metadata-Version: 2.1
Name: sum-arun-test
Version: 0.1.3
Summary: A Python SDK for Testing sdk
Author: Arun Uday
